MANIFEST.in
README.rst
activate-jj.sh
setup.py
jj_menu/__init__.py
jj_menu/jj_menu.py
jj_menu.egg-info/PKG-INFO
jj_menu.egg-info/SOURCES.txt
jj_menu.egg-info/dependency_links.txt
jj_menu.egg-info/entry_points.txt
jj_menu.egg-info/requires.txt
jj_menu.egg-info/top_level.txt