Metadata-Version: 1.0
Name: jj-menu
Version: 0.2.1
Summary: Simple CUI (TUI) Launcher menu
Home-page: https://github.com/ytyng/jj-menu.git
Author: ytyng
Author-email: ytyng@live.jp
License: BSD
Keywords: CUI,TUI,Launcher,Python,curses
Platform: UNKNOWN
